src/Observation.py
src/__init__.py
limmi_fhir-0.4.dist-info/METADATA
limmi_fhir-0.4.dist-info/WHEEL
limmi_fhir-0.4.dist-info/top_level.txt
limmi_fhir-0.4.dist-info/RECORD
