Metadata-Version: 2.1
Name: limmi_fhir
Version: 0.4
Summary: Limmi FHIR Resource Library
Home-page: https://github.com/yourusername/mypackage
Author: Limmi, Inc.
Author-email: todd@mentorhead.io
